warsawbuspy/__init__.py
warsawbuspy/analyzers/__init__.py
warsawbuspy/analyzers/data_analyzer.py
warsawbuspy/analyzers/data_comparator.py
warsawbuspy/analyzers/data_visualizer.py
warsawbuspy/holders/__init__.py
warsawbuspy/holders/data_holders.py
warsawbuspy/readers/__init__.py
warsawbuspy/readers/data_reader.py
warsawbuspy/utility/__init__.py
warsawbuspy/utility/data_utility.py
warsawbuspy/utility/exceptions.py
warsawbuspy-1.0.5.dist-info/METADATA
warsawbuspy-1.0.5.dist-info/WHEEL
warsawbuspy-1.0.5.dist-info/licenses/LICENSE
warsawbuspy-1.0.5.dist-info/RECORD
