Metadata-Version: 2.1
Name: warsawbuspy
Version: 1.0.5
Summary: A package containing a functionality of readint the data from the https://api.um.warszawa.pl, analyzing it and displaying results of the analyzis.
Project-URL: Homepage, https://github.com/GustawB/BUS_DATA_READER
Project-URL: Issues, https://github.com/GustawB/BUS_DATA_READER/issues
Author-email: Gustaw Blachowski <gustaw.blachowski@gmail.com>
License-File: LICENSE
Classifier: License :: OSI Approved :: MIT License
Classifier: Operating System :: OS Independent
Classifier: Programming Language :: Python :: 3
Requires-Python: >=3.0
Requires-Dist: datetime>=5.4
Requires-Dist: geopandas>=0.14.3
Requires-Dist: matplotlib>=3.8.2
Requires-Dist: pandas>=2.2.0
Requires-Dist: requests>=2.31.0
